{"data":{"site":{"siteMetadata":{"title":"Steveostudios"}},"allMarkdownRemark":{"edges":[{"node":{"excerpt":"99% of articles and tutorials about Git will tell you that Git is super important because it helps you with collaboration. Features and bug…","fields":{"slug":"/git-solo/"},"frontmatter":{"date":"April 02, 2019","title":"Git for Solo Development"}}},{"node":{"excerpt":"I’m old school. I started out designing websites in Photoshop (remember slicing up mockups) and dropping them into Flash or Dreamweaver! But…","fields":{"slug":"/hello-world/"},"frontmatter":{"date":"March 23, 2019","title":"Design Wars"}}}]}},"pageContext":{"isCreatedByStatefulCreatePages":true}}